[{"train_id":2,"train_name":"Ulrich","train_depart":"Oxnam","train_arrival":"Jequié Airport","train_coach":"SA"},
  {"train_id":3,"train_name":"Mella","train_depart":"Adelberg","train_arrival":"Paamiut Airport","train_coach":"NA"},
  {"train_id":4,"train_name":"Minna","train_depart":"Luparti","train_arrival":"Utti Air Base","train_coach":"EU"},
  {"train_id":5,"train_name":"Seamus","train_depart":"Pierrepoint","train_arrival":"Rajouri Airport","train_coach":"AS"},
  {"train_id":6,"train_name":"Dinny","train_depart":"Otham","train_arrival":"Weedon Field","train_coach":"NA"},
  {"train_id":7,"train_name":"Kane","train_depart":"Toovey","train_arrival":"Dios Airport","train_coach":"OC"},
  {"train_id":8,"train_name":"Lucy","train_depart":"Bulled","train_arrival":"Jabot Airport","train_coach":"OC"},
  {"train_id":9,"train_name":"Carry","train_depart":"Bartoshevich","train_arrival":"Chandler Field","train_coach":"NA"},
  {"train_id":10,"train_name":"Dre","train_depart":"Gatrill","train_arrival":"New Chitose Airport","train_coach":"AS"},
  {"train_id":11,"train_name":"Betsey","train_depart":"Seeking","train_arrival":"Greenvale Airport","train_coach":"OC"},
  {"train_id":12,"train_name":"Chilton","train_depart":"Titterrell","train_arrival":"Faaite Airport","train_coach":"OC"},
  {"train_id":13,"train_name":"Coralyn","train_depart":"Brogini","train_arrival":"La Roche-sur-Yon Airport","train_coach":"EU"},
  {"train_id":14,"train_name":"Sherm","train_depart":"Bingall","train_arrival":"Nikolski Air Station","train_coach":"NA"}]
